{
	"$schema": "../../../arkini.schema.json",
	"items": {
		"producer:library-t4": {
			"description": "Grand library that researches and reissues every currently available blueprint through the final era.",
			"effects": [
				{
					"grants": [
						{
							"id": "grant:owned:producer:library-t4",
							"name": "Owns Library IV"
						}
					],
					"id": "effect:grant-owned:producer-library-t4",
					"name": "Owned Library IV grant",
					"polarity": "neutral",
					"sourceScope": "both"
				}
			],
			"maxCount": 1,
			"maxStackSize": 1,
			"name": "Library IV",
			"tags": [
				"producer",
				"building",
				"library",
				"blueprint",
				"knowledge",
				"unique",
				"era:XI"
			],
			"tier": 11
		}
	}
}
